prepnlp/__init__.py
prepnlp/base.py
prepnlp/semeval.py
tests/__init__.py
tests/test_semeval.py
prepnlp-0.0.6.dist-info/LICENSE
prepnlp-0.0.6.dist-info/METADATA
prepnlp-0.0.6.dist-info/WHEEL
prepnlp-0.0.6.dist-info/top_level.txt
prepnlp-0.0.6.dist-info/RECORD
