Metadata-Version: 2.1
Name: prepnlp
Version: 0.0.6
Summary: Lightweight utilities to train nlp tasks for deep learning
Home-page: https://github.com/ariepratama/prepnlp
Author: Arie Pratama Sutiono
License: UNKNOWN
Platform: UNKNOWN
Requires-Python: >=3.5
